odoo10_addon_printer_tray-10.0.1.0.0-py2.7-nspkg.pth
odoo/addons/printer_tray/README.rst
odoo/addons/printer_tray/__init__.py
odoo/addons/printer_tray/__manifest__.py
odoo/addons/printer_tray/i18n/am.po
odoo/addons/printer_tray/i18n/bg.po
odoo/addons/printer_tray/i18n/ca.po
odoo/addons/printer_tray/i18n/de.po
odoo/addons/printer_tray/i18n/el_GR.po
odoo/addons/printer_tray/i18n/es.po
odoo/addons/printer_tray/i18n/es_ES.po
odoo/addons/printer_tray/i18n/fi.po
odoo/addons/printer_tray/i18n/fr.po
odoo/addons/printer_tray/i18n/gl.po
odoo/addons/printer_tray/i18n/hr.po
odoo/addons/printer_tray/i18n/hr_HR.po
odoo/addons/printer_tray/i18n/it.po
odoo/addons/printer_tray/i18n/nl.po
odoo/addons/printer_tray/i18n/printer_tray.po
odoo/addons/printer_tray/i18n/pt.po
odoo/addons/printer_tray/i18n/pt_BR.po
odoo/addons/printer_tray/i18n/pt_PT.po
odoo/addons/printer_tray/i18n/sl.po
odoo/addons/printer_tray/i18n/tr.po
odoo/addons/printer_tray/i18n/zh_CN.po
odoo/addons/printer_tray/models/__init__.py
odoo/addons/printer_tray/models/ir_actions_report_xml.py
odoo/addons/printer_tray/models/printing_printer.py
odoo/addons/printer_tray/models/printing_report_xml_action.py
odoo/addons/printer_tray/models/printing_tray.py
odoo/addons/printer_tray/models/res_users.py
odoo/addons/printer_tray/security/ir.model.access.csv
odoo/addons/printer_tray/tests/__init__.py
odoo/addons/printer_tray/tests/test_ir_actions_report_xml.py
odoo/addons/printer_tray/tests/test_printing_printer.py
odoo/addons/printer_tray/tests/test_printing_report_xml_action.py
odoo/addons/printer_tray/tests/test_printing_tray.py
odoo/addons/printer_tray/tests/test_res_users.py
odoo/addons/printer_tray/views/ir_actions_report_xml.xml
odoo/addons/printer_tray/views/printing_printer.xml
odoo/addons/printer_tray/views/printing_report_xml_action.xml
odoo/addons/printer_tray/views/res_users.xml
odoo10_addon_printer_tray-10.0.1.0.0.dist-info/DESCRIPTION.rst
odoo10_addon_printer_tray-10.0.1.0.0.dist-info/METADATA
odoo10_addon_printer_tray-10.0.1.0.0.dist-info/RECORD
odoo10_addon_printer_tray-10.0.1.0.0.dist-info/WHEEL
odoo10_addon_printer_tray-10.0.1.0.0.dist-info/metadata.json
odoo10_addon_printer_tray-10.0.1.0.0.dist-info/namespace_packages.txt
odoo10_addon_printer_tray-10.0.1.0.0.dist-info/top_level.txt
