Metadata-Version: 2.0
Name: odoo10-addon-printer-tray
Version: 10.0.1.0.0
Summary: Report to printer - Paper tray selection
Home-page: http://www.camptocamp.com/
Author: Camptocamp, Odoo Community Association (OCA)
Author-email: support@odoo-community.org
License: AGPL-3
Platform: UNKNOWN
Classifier: Programming Language :: Python :: 2.7
Classifier: Framework :: Odoo
Classifier: License :: OSI Approved :: GNU Affero General Public License v3
Requires-Dist: odoo (<10.1dev,>=10.0)
Requires-Dist: odoo10-addon-base-report-to-printer
Requires-Dist: pycups
